correlation_stats_analyzer/__init__.py
correlation_stats_analyzer/correlation_stats_analyzer.py
correlation_stats_analyzer-0.1.1.dist-info/License
correlation_stats_analyzer-0.1.1.dist-info/METADATA
correlation_stats_analyzer-0.1.1.dist-info/WHEEL
correlation_stats_analyzer-0.1.1.dist-info/top_level.txt
correlation_stats_analyzer-0.1.1.dist-info/RECORD
