Metadata-Version: 2.1
Name: correlation-stats-analyzer
Version: 0.1.1
Summary: A simple tool to compute and interpret Pearson correlation coefficients.
Author: Md. Ismiel Hossen Abir
Author-email: ismielabir1971@gmail.com
Classifier: Programming Language :: Python :: 3
Classifier: Topic :: Scientific/Engineering :: Information Analysis
Classifier: License :: OSI Approved :: MIT License
Classifier: Operating System :: OS Independent
Requires-Python: >=3.6
License-File: License
